akioi_2048/__init__.py
akioi_2048/__init__.pyi
akioi_2048/akioi_2048.abi3.so
akioi_2048-0.5.1.dist-info/METADATA
akioi_2048-0.5.1.dist-info/WHEEL
akioi_2048-0.5.1.dist-info/RECORD
akioi_2048-0.5.1.dist-info/licenses/LICENSE
