Metadata-Version: 2.4
Name: akioi-2048
Version: 0.5.1
License-File: LICENSE
Summary: akioi backend
Author: jasonxue
Requires-Python: >=3.8, <3.14
